jrpyefficient/Makefile
jrpyefficient/__init__.py
jrpyefficient/__version__.py
jrpyefficient/data.py
jrpyefficient/get_numeric_list.py
jrpyefficient/vignettes.py
jrpyefficient-0.0.1.dist-info/WHEEL
jrpyefficient-0.0.1.dist-info/METADATA
jrpyefficient-0.0.1.dist-info/RECORD
