Metadata-Version: 2.1
Name: jrpyefficient
Version: 0.0.1
Summary: Jumping Rivers: Efficient Data Science in Python
Author: Jumping Rivers
Author-email: info@jumpingrivers.com
Requires-Python: >=3.7
Classifier: Programming Language :: Python :: 3
Classifier: Programming Language :: Python :: 3.10
Classifier: Programming Language :: Python :: 3.7
Classifier: Programming Language :: Python :: 3.8
Classifier: Programming Language :: Python :: 3.9
